{
  "libVersion": "3.6.6",
  "projectname": "photo-to-pdf",
  "condition": {
    "miniprogram": {
      "list": [
        {
          "name": "pages/history/history",
          "pathName": "pages/history/history",
          "query": "",
          "scene": null,
          "launchMode": "default"
        }
      ]
    }
  },
  "setting": {
    "urlCheck": false,
    "coverView": true,
    "lazyloadPlaceholderEnable": false,
    "skylineRenderEnable": false,
    "preloadBackgroundData": false,
    "autoAudits": false,
    "useApiHook": true,
    "useApiHostProcess": true,
    "showShadowRootInWxmlPanel": true,
    "useStaticServer": false,
    "useLanDebug": false,
    "showES6CompileOption": false,
    "compileHotReLoad": true,
    "checkInvalidKey": true,
    "ignoreDevUnusedFiles": true,
    "bigPackageSizeSupport": false,
    "useIsolateContext": true
  }
}